{
  "key" : 7250595,
  "kingdom" : "Fungi",
  "phylum" : "Ascomycota",
  "clazz" : "Lecanoromycetes",
  "order" : "Peltigerales",
  "family" : "Collemataceae",
  "genus" : "Leptogium",
  "subgenus" : null,
  "species" : "Leptogium bullatum",
  "kingdomKey" : 5,
  "phylumKey" : 95,
  "classKey" : 180,
  "orderKey" : 1055,
  "familyKey" : 8377,
  "genusKey" : 2600911,
  "subgenusKey" : null,
  "speciesKey" : 7250595,
  "datasetKey" : "d7dddbf4-2cf0-4f39-9b2a-bb099caae36c",
  "constituentKey" : null,
  "nubKey" : 7250595,
  "parentKey" : 2600911,
  "parent" : "Leptogium",
  "proParteKey" : null,
  "acceptedKey" : null,
  "accepted" : null,
  "basionymKey" : 3307938,
  "basionym" : "Lichen bullatus Menzies",
  "scientificName" : "Leptogium bullatum (Sw.) Mont.",
  "canonicalName" : "Leptogium bullatum",
  "vernacularName" : null,
  "authorship" : "Mont. (Sw.)",
  "nameType" : "WELLFORMED",
  "rank" : "SPECIES",
  "origin" : "SOURCE",
  "taxonomicStatus" : "ACCEPTED",
  "nomenclaturalStatus" : [ ],
  "remarks" : null,
  "publishedIn" : "Annls Sci. Nat. , Bot. , sér. 2 16: 133 (1841)",
  "accordingTo" : "Index Fungorum",
  "numDescendants" : 2,
  "identifiers" : [ {
    "key" : null,
    "usageKey" : null,
    "datasetKey" : null,
    "identifier" : "110193047",
    "title" : null,
    "type" : "SOURCE_ID",
    "identifierLink" : null
  } ],
  "synonym" : false,
  "link" : null,
  "sourceId" : "110193047"
}