{
  "key" : 6326672,
  "kingdom" : "Fungi",
  "phylum" : "Basidiomycota",
  "clazz" : "Agaricomycetes",
  "order" : "Thelephorales",
  "family" : "Thelephoraceae",
  "genus" : "Tomentella",
  "subgenus" : null,
  "species" : "Hypochnus incarnatus",
  "kingdomKey" : 5,
  "phylumKey" : 34,
  "classKey" : 186,
  "orderKey" : 530,
  "familyKey" : 3277,
  "genusKey" : 5237005,
  "subgenusKey" : null,
  "speciesKey" : 6326672,
  "datasetKey" : "d7dddbf4-2cf0-4f39-9b2a-bb099caae36c",
  "constituentKey" : null,
  "nubKey" : 6326672,
  "parentKey" : 5237005,
  "parent" : "Tomentella",
  "proParteKey" : null,
  "acceptedKey" : null,
  "accepted" : null,
  "basionymKey" : 6326672,
  "basionym" : "Hypochnus incarnatus Schleich.",
  "scientificName" : "Hypochnus incarnatus Schleich.",
  "canonicalName" : "Hypochnus incarnatus",
  "vernacularName" : null,
  "authorship" : "Schleich.",
  "nameType" : "WELLFORMED",
  "rank" : "SPECIES",
  "origin" : "SOURCE",
  "taxonomicStatus" : "ACCEPTED",
  "nomenclaturalStatus" : [ ],
  "remarks" : null,
  "publishedIn" : "Catalogus Plant. Helvetia 58 (1821)",
  "accordingTo" : "Index Fungorum",
  "numDescendants" : 0,
  "identifiers" : [ {
    "key" : null,
    "usageKey" : null,
    "datasetKey" : null,
    "identifier" : "110000727",
    "title" : null,
    "type" : "SOURCE_ID",
    "identifierLink" : null
  } ],
  "synonym" : false,
  "link" : null,
  "sourceId" : "110000727"
}