{
  "key" : 7241860,
  "kingdom" : "Fungi",
  "phylum" : "Basidiomycota",
  "clazz" : "Agaricomycetes",
  "order" : "Cantharellales",
  "family" : "Cantharellaceae",
  "genus" : "Trombetta",
  "subgenus" : null,
  "species" : null,
  "kingdomKey" : 5,
  "phylumKey" : 34,
  "classKey" : 186,
  "orderKey" : 1300,
  "familyKey" : 8457,
  "genusKey" : 7241860,
  "subgenusKey" : null,
  "speciesKey" : null,
  "datasetKey" : "d7dddbf4-2cf0-4f39-9b2a-bb099caae36c",
  "constituentKey" : null,
  "nubKey" : 7241860,
  "parentKey" : 8457,
  "parent" : "Cantharellaceae",
  "proParteKey" : null,
  "acceptedKey" : null,
  "accepted" : null,
  "basionymKey" : null,
  "basionym" : null,
  "scientificName" : "Trombetta",
  "canonicalName" : "Trombetta",
  "vernacularName" : null,
  "authorship" : "",
  "nameType" : "WELLFORMED",
  "rank" : "GENUS",
  "origin" : "SOURCE",
  "taxonomicStatus" : "ACCEPTED",
  "nomenclaturalStatus" : [ ],
  "remarks" : null,
  "publishedIn" : null,
  "accordingTo" : "Index Fungorum",
  "numDescendants" : 17,
  "identifiers" : [ {
    "key" : null,
    "usageKey" : null,
    "datasetKey" : null,
    "identifier" : "110218120",
    "title" : null,
    "type" : "SOURCE_ID",
    "identifierLink" : null
  } ],
  "synonym" : false,
  "link" : null,
  "sourceId" : "110218120"
}