{
  "key" : 2579525,
  "kingdom" : "Fungi",
  "phylum" : "Ascomycota",
  "clazz" : "Leotiomycetes",
  "order" : "Rhytismatales",
  "family" : "Rhytismataceae",
  "genus" : "Hypodermella",
  "subgenus" : null,
  "species" : "Hypodermella laricis",
  "kingdomKey" : 5,
  "phylumKey" : 95,
  "classKey" : 179,
  "orderKey" : 1278,
  "familyKey" : 8281,
  "genusKey" : 2579523,
  "subgenusKey" : null,
  "speciesKey" : 2579524,
  "datasetKey" : "d7dddbf4-2cf0-4f39-9b2a-bb099caae36c",
  "constituentKey" : null,
  "nubKey" : 2579525,
  "parentKey" : 2579523,
  "parent" : "Hypodermella",
  "proParteKey" : null,
  "acceptedKey" : 2579524,
  "accepted" : "Hypodermella laricis Tubeuf, 1895",
  "basionymKey" : 2579525,
  "basionym" : "Hypodermella laricis var. octospora Dearn., 1926",
  "scientificName" : "Hypodermella laricis var. octospora Dearn., 1926",
  "canonicalName" : "Hypodermella laricis octospora",
  "vernacularName" : null,
  "authorship" : "Dearn., 1926",
  "nameType" : "WELLFORMED",
  "rank" : "VARIETY",
  "origin" : "SOURCE",
  "taxonomicStatus" : "SYNONYM",
  "nomenclaturalStatus" : [ ],
  "remarks" : null,
  "publishedIn" : "Mycologia 18(5): 241 (1926)",
  "accordingTo" : "The Catalogue of Life, 3rd January 2011",
  "numDescendants" : 0,
  "identifiers" : [ {
    "key" : null,
    "usageKey" : null,
    "datasetKey" : null,
    "identifier" : "120202253",
    "title" : null,
    "type" : "SOURCE_ID",
    "identifierLink" : null
  } ],
  "synonym" : true,
  "link" : null,
  "sourceId" : "120202253"
}