{
  "key" : 2577334,
  "kingdom" : "Fungi",
  "phylum" : "Ascomycota",
  "clazz" : "Sordariomycetes",
  "order" : "Xylariales",
  "family" : "Xylariaceae",
  "genus" : "Anthostomella",
  "subgenus" : null,
  "species" : "Anthostomella clypeata",
  "kingdomKey" : 5,
  "phylumKey" : 95,
  "classKey" : 320,
  "orderKey" : 1298,
  "familyKey" : 4168,
  "genusKey" : 2567306,
  "subgenusKey" : null,
  "speciesKey" : 2577334,
  "datasetKey" : "d7dddbf4-2cf0-4f39-9b2a-bb099caae36c",
  "constituentKey" : null,
  "nubKey" : 2577334,
  "parentKey" : 2567306,
  "parent" : "Anthostomella",
  "proParteKey" : null,
  "acceptedKey" : null,
  "accepted" : null,
  "basionymKey" : 2577335,
  "basionym" : "Discosia clypeata De Not.",
  "scientificName" : "Anthostomella clypeata (De Not.) Sacc., 1882",
  "canonicalName" : "Anthostomella clypeata",
  "vernacularName" : null,
  "authorship" : "Sacc., 1882 (De Not.)",
  "nameType" : "WELLFORMED",
  "rank" : "SPECIES",
  "origin" : "SOURCE",
  "taxonomicStatus" : "ACCEPTED",
  "nomenclaturalStatus" : [ ],
  "remarks" : null,
  "publishedIn" : "Syll. fung. (Abellini) 1: 283 (1882)",
  "accordingTo" : "The Catalogue of Life, 3rd January 2011",
  "numDescendants" : 7,
  "identifiers" : [ {
    "key" : null,
    "usageKey" : null,
    "datasetKey" : null,
    "identifier" : "120209775",
    "title" : null,
    "type" : "SOURCE_ID",
    "identifierLink" : null
  } ],
  "synonym" : false,
  "link" : null,
  "sourceId" : "120209775"
}