{
  "key" : 3301897,
  "kingdom" : "Fungi",
  "phylum" : "Ascomycota",
  "clazz" : "Sordariomycetes",
  "order" : null,
  "family" : "Magnaporthaceae",
  "genus" : "Clasterosporium",
  "subgenus" : null,
  "species" : "Hymenopodium sarcopodioides",
  "kingdomKey" : 5,
  "phylumKey" : 95,
  "classKey" : 320,
  "orderKey" : null,
  "familyKey" : 5731,
  "genusKey" : 2569234,
  "subgenusKey" : null,
  "speciesKey" : 3301897,
  "datasetKey" : "d7dddbf4-2cf0-4f39-9b2a-bb099caae36c",
  "constituentKey" : null,
  "nubKey" : 3301897,
  "parentKey" : 2569234,
  "parent" : "Clasterosporium",
  "proParteKey" : null,
  "acceptedKey" : null,
  "accepted" : null,
  "basionymKey" : 3301897,
  "basionym" : "Hymenopodium sarcopodioides Corda",
  "scientificName" : "Hymenopodium sarcopodioides Corda",
  "canonicalName" : "Hymenopodium sarcopodioides",
  "vernacularName" : null,
  "authorship" : "Corda",
  "nameType" : "WELLFORMED",
  "rank" : "SPECIES",
  "origin" : "SOURCE",
  "taxonomicStatus" : "ACCEPTED",
  "nomenclaturalStatus" : [ ],
  "remarks" : null,
  "publishedIn" : "Icon. fung. (Prague) 1: 7 (1837)",
  "accordingTo" : "Index Fungorum",
  "numDescendants" : 0,
  "identifiers" : [ {
    "key" : null,
    "usageKey" : null,
    "datasetKey" : null,
    "identifier" : "109957440",
    "title" : null,
    "type" : "SOURCE_ID",
    "identifierLink" : null
  } ],
  "synonym" : false,
  "link" : null,
  "sourceId" : "109957440"
}