{
  "key" : 2556674,
  "kingdom" : "Fungi",
  "phylum" : "Basidiomycota",
  "clazz" : "Ustilaginomycetes",
  "order" : "Urocystidiales",
  "family" : "Urocystidaceae",
  "genus" : "Ustacystis",
  "subgenus" : null,
  "species" : "Ustacystis waldsteiniae",
  "kingdomKey" : 5,
  "phylumKey" : 34,
  "classKey" : 148,
  "orderKey" : 1122,
  "familyKey" : 3825,
  "genusKey" : 2556673,
  "subgenusKey" : null,
  "speciesKey" : 2556674,
  "datasetKey" : "d7dddbf4-2cf0-4f39-9b2a-bb099caae36c",
  "constituentKey" : null,
  "nubKey" : 2556674,
  "parentKey" : 2556673,
  "parent" : "Ustacystis",
  "proParteKey" : null,
  "acceptedKey" : null,
  "accepted" : null,
  "basionymKey" : 5250082,
  "basionym" : "Urocystis waldsteiniae Peck, 1893",
  "scientificName" : "Ustacystis waldsteiniae (Peck) Zundel, 1945",
  "canonicalName" : "Ustacystis waldsteiniae",
  "vernacularName" : null,
  "authorship" : "Zundel, 1945 (Peck)",
  "nameType" : "WELLFORMED",
  "rank" : "SPECIES",
  "origin" : "SOURCE",
  "taxonomicStatus" : "ACCEPTED",
  "nomenclaturalStatus" : [ ],
  "remarks" : null,
  "publishedIn" : "Mycologia 37(6): 796 (1945)",
  "accordingTo" : "The Catalogue of Life, 3rd January 2011",
  "numDescendants" : 0,
  "identifiers" : [ {
    "key" : null,
    "usageKey" : null,
    "datasetKey" : null,
    "identifier" : "120218420",
    "title" : null,
    "type" : "SOURCE_ID",
    "identifierLink" : null
  } ],
  "synonym" : false,
  "link" : null,
  "sourceId" : "120218420"
}