{
  "key" : 6148101,
  "kingdom" : "Protozoa",
  "phylum" : "Ciliophora",
  "clazz" : "Gymnostomatea",
  "order" : "Pleurostomatida",
  "family" : "Litonotidae",
  "genus" : "Acineria",
  "subgenus" : null,
  "species" : "Acineria brevicaulis",
  "kingdomKey" : 7,
  "phylumKey" : 10,
  "classKey" : 6147094,
  "orderKey" : 6147729,
  "familyKey" : 3237077,
  "genusKey" : 4888754,
  "subgenusKey" : null,
  "speciesKey" : 6148101,
  "datasetKey" : "d7dddbf4-2cf0-4f39-9b2a-bb099caae36c",
  "constituentKey" : null,
  "nubKey" : 6148101,
  "parentKey" : 4888754,
  "parent" : "Acineria",
  "proParteKey" : null,
  "acceptedKey" : null,
  "accepted" : null,
  "basionymKey" : null,
  "basionym" : null,
  "scientificName" : "Acineria brevicaulis",
  "canonicalName" : "Acineria brevicaulis",
  "vernacularName" : null,
  "authorship" : "",
  "nameType" : "WELLFORMED",
  "rank" : "SPECIES",
  "origin" : "SOURCE",
  "taxonomicStatus" : "ACCEPTED",
  "nomenclaturalStatus" : [ ],
  "remarks" : null,
  "publishedIn" : null,
  "accordingTo" : "The Catalogue of Life, 3rd January 2011",
  "numDescendants" : 0,
  "identifiers" : [ {
    "key" : null,
    "usageKey" : null,
    "datasetKey" : null,
    "identifier" : "118535748",
    "title" : null,
    "type" : "SOURCE_ID",
    "identifierLink" : null
  } ],
  "synonym" : false,
  "link" : null,
  "sourceId" : "118535748"
}