{
  "key" : 3313751,
  "kingdom" : "Fungi",
  "phylum" : "Basidiomycota",
  "clazz" : "Agaricomycetes",
  "order" : "Agaricales",
  "family" : "Typhulaceae",
  "genus" : "Sclerotium",
  "subgenus" : null,
  "species" : "Sclerotium lycopodii",
  "kingdomKey" : 5,
  "phylumKey" : 34,
  "classKey" : 186,
  "orderKey" : 1499,
  "familyKey" : 7007,
  "genusKey" : 2513145,
  "subgenusKey" : null,
  "speciesKey" : 3313751,
  "datasetKey" : "d7dddbf4-2cf0-4f39-9b2a-bb099caae36c",
  "constituentKey" : null,
  "nubKey" : 3313751,
  "parentKey" : 2513145,
  "parent" : "Sclerotium",
  "proParteKey" : null,
  "acceptedKey" : null,
  "accepted" : null,
  "basionymKey" : 3313751,
  "basionym" : "Sclerotium lycopodii Fr.",
  "scientificName" : "Sclerotium lycopodii Fr.",
  "canonicalName" : "Sclerotium lycopodii",
  "vernacularName" : null,
  "authorship" : "Fr.",
  "nameType" : "WELLFORMED",
  "rank" : "SPECIES",
  "origin" : "SOURCE",
  "taxonomicStatus" : "ACCEPTED",
  "nomenclaturalStatus" : [ ],
  "remarks" : null,
  "publishedIn" : "Syst. mycol. (Lundae) 2(1): 257 (1822)",
  "accordingTo" : "Index Fungorum",
  "numDescendants" : 0,
  "identifiers" : [ {
    "key" : null,
    "usageKey" : null,
    "datasetKey" : null,
    "identifier" : "109798089",
    "title" : null,
    "type" : "SOURCE_ID",
    "identifierLink" : null
  } ],
  "synonym" : false,
  "link" : null,
  "sourceId" : "109798089"
}