{
  "key" : 3196051,
  "kingdom" : "Chromista",
  "phylum" : "Ochrophyta",
  "clazz" : "Phaeophyceae",
  "order" : "Laminariales",
  "family" : "Laminariaceae",
  "genus" : "Laminaria",
  "subgenus" : null,
  "species" : null,
  "kingdomKey" : 4,
  "phylumKey" : 98,
  "classKey" : 7073593,
  "orderKey" : 560,
  "familyKey" : 7740,
  "genusKey" : 3195825,
  "subgenusKey" : null,
  "speciesKey" : null,
  "datasetKey" : "d7dddbf4-2cf0-4f39-9b2a-bb099caae36c",
  "constituentKey" : null,
  "nubKey" : 3196051,
  "parentKey" : 7740,
  "parent" : "Laminariaceae",
  "proParteKey" : null,
  "acceptedKey" : 3195825,
  "accepted" : "Laminaria J.V.F. Lamouroux, 1813",
  "basionymKey" : null,
  "basionym" : null,
  "scientificName" : "Hafgygia Kützing, 1843",
  "canonicalName" : "Hafgygia",
  "vernacularName" : null,
  "authorship" : "Kützing, 1843",
  "nameType" : "WELLFORMED",
  "rank" : "GENUS",
  "origin" : "SOURCE",
  "taxonomicStatus" : "SYNONYM",
  "nomenclaturalStatus" : [ ],
  "remarks" : null,
  "publishedIn" : null,
  "accordingTo" : "World Register of Marine Species",
  "numDescendants" : 0,
  "identifiers" : [ {
    "key" : null,
    "usageKey" : null,
    "datasetKey" : null,
    "identifier" : "109754724",
    "title" : null,
    "type" : "SOURCE_ID",
    "identifierLink" : null
  } ],
  "synonym" : true,
  "link" : null,
  "sourceId" : "109754724"
}