{
  "key" : 7258360,
  "kingdom" : "Fungi",
  "phylum" : "Ascomycota",
  "clazz" : null,
  "order" : null,
  "family" : null,
  "genus" : "Abrothallus",
  "subgenus" : null,
  "species" : "Abrothallus usneae",
  "kingdomKey" : 5,
  "phylumKey" : 95,
  "classKey" : null,
  "orderKey" : null,
  "familyKey" : null,
  "genusKey" : 2584324,
  "subgenusKey" : null,
  "speciesKey" : 2592364,
  "datasetKey" : "d7dddbf4-2cf0-4f39-9b2a-bb099caae36c",
  "constituentKey" : null,
  "nubKey" : 7258360,
  "parentKey" : 2592364,
  "parent" : "Abrothallus usneae",
  "proParteKey" : null,
  "acceptedKey" : null,
  "accepted" : null,
  "basionymKey" : null,
  "basionym" : null,
  "scientificName" : "Abrothallus usneae var. usneae",
  "canonicalName" : "Abrothallus usneae usneae",
  "vernacularName" : null,
  "authorship" : "",
  "nameType" : "WELLFORMED",
  "rank" : "VARIETY",
  "origin" : "AUTONYM",
  "taxonomicStatus" : "ACCEPTED",
  "nomenclaturalStatus" : [ ],
  "remarks" : null,
  "publishedIn" : null,
  "accordingTo" : "NUB Generator [autonym]",
  "numDescendants" : 0,
  "identifiers" : [ ],
  "synonym" : false,
  "link" : null,
  "sourceId" : null
}