{
  "key" : 3284123,
  "kingdom" : "Fungi",
  "phylum" : "Ascomycota",
  "clazz" : "Saccharomycetes",
  "order" : "Saccharomycetales",
  "family" : "Saccharomycetaceae",
  "genus" : "Zygofabospora",
  "subgenus" : null,
  "species" : "Zygofabospora lactis",
  "kingdomKey" : 5,
  "phylumKey" : 95,
  "classKey" : 182,
  "orderKey" : 1281,
  "familyKey" : 4140,
  "genusKey" : 7245494,
  "subgenusKey" : null,
  "speciesKey" : 7245495,
  "datasetKey" : "d7dddbf4-2cf0-4f39-9b2a-bb099caae36c",
  "constituentKey" : null,
  "nubKey" : 3284123,
  "parentKey" : 7245495,
  "parent" : "Zygofabospora lactis",
  "proParteKey" : null,
  "acceptedKey" : null,
  "accepted" : null,
  "basionymKey" : 3478725,
  "basionym" : "Saccharomyces drosophilarum Shehata, Mrak & Phaff",
  "scientificName" : "Zygofabospora lactis var. drosophilarum (Shehata, Mrak & Phaff) G.I. Naumov",
  "canonicalName" : "Zygofabospora lactis drosophilarum",
  "vernacularName" : null,
  "authorship" : "G.I. Naumov (Shehata, Mrak & Phaff)",
  "nameType" : "WELLFORMED",
  "rank" : "VARIETY",
  "origin" : "SOURCE",
  "taxonomicStatus" : "ACCEPTED",
  "nomenclaturalStatus" : [ ],
  "remarks" : null,
  "publishedIn" : "in Naumov & Naumova, FEMS Yeast Res. 2(1): 44 (2002)",
  "accordingTo" : "Index Fungorum",
  "numDescendants" : 0,
  "identifiers" : [ {
    "key" : null,
    "usageKey" : null,
    "datasetKey" : null,
    "identifier" : "109979309",
    "title" : null,
    "type" : "SOURCE_ID",
    "identifierLink" : null
  } ],
  "synonym" : false,
  "link" : null,
  "sourceId" : "109979309"
}