{
  "key" : 5260005,
  "kingdom" : "Fungi",
  "phylum" : "Ascomycota",
  "clazz" : "Eurotiomycetes",
  "order" : "Eurotiales",
  "family" : "Trichocomaceae",
  "genus" : "Aspergillus",
  "subgenus" : null,
  "species" : "Aspergillus homomorphus",
  "kingdomKey" : 5,
  "phylumKey" : 95,
  "classKey" : 178,
  "orderKey" : 1040,
  "familyKey" : 8324,
  "genusKey" : 2518427,
  "subgenusKey" : null,
  "speciesKey" : 5260005,
  "datasetKey" : "d7dddbf4-2cf0-4f39-9b2a-bb099caae36c",
  "constituentKey" : null,
  "nubKey" : 5260005,
  "parentKey" : 2518427,
  "parent" : "Aspergillus",
  "proParteKey" : null,
  "acceptedKey" : null,
  "accepted" : null,
  "basionymKey" : 5260005,
  "basionym" : "Aspergillus homomorphus Steiman, Guiraud, Sage & Seigle-Mur. ex Samson & Frisvad, 2004",
  "scientificName" : "Aspergillus homomorphus Steiman, Guiraud, Sage & Seigle-Mur. ex Samson & Frisvad, 2004",
  "canonicalName" : "Aspergillus homomorphus",
  "vernacularName" : null,
  "authorship" : "Steiman, Guiraud, Sage & Seigle-Mur. ex Samson & Frisvad, 2004",
  "nameType" : "WELLFORMED",
  "rank" : "SPECIES",
  "origin" : "SOURCE",
  "taxonomicStatus" : "ACCEPTED",
  "nomenclaturalStatus" : [ ],
  "remarks" : null,
  "publishedIn" : "in Samson, Houbraken, Kuijpers, Frank & Frisvad, Stud. Mycol. 50(1): 58 (2004)",
  "accordingTo" : "The Catalogue of Life, 3rd January 2011",
  "numDescendants" : 0,
  "identifiers" : [ {
    "key" : null,
    "usageKey" : null,
    "datasetKey" : null,
    "identifier" : "120233736",
    "title" : null,
    "type" : "SOURCE_ID",
    "identifierLink" : null
  } ],
  "synonym" : false,
  "link" : null,
  "sourceId" : "120233736"
}