{
  "key" : 2596383,
  "kingdom" : "Fungi",
  "phylum" : "Ascomycota",
  "clazz" : "Eurotiomycetes",
  "order" : "Onygenales",
  "family" : "Onygenaceae",
  "genus" : "Bifidocarpus",
  "subgenus" : null,
  "species" : null,
  "kingdomKey" : 5,
  "phylumKey" : 95,
  "classKey" : 178,
  "orderKey" : 1041,
  "familyKey" : 4832,
  "genusKey" : 2596383,
  "subgenusKey" : null,
  "speciesKey" : null,
  "datasetKey" : "d7dddbf4-2cf0-4f39-9b2a-bb099caae36c",
  "constituentKey" : null,
  "nubKey" : 2596383,
  "parentKey" : 4832,
  "parent" : "Onygenaceae",
  "proParteKey" : null,
  "acceptedKey" : null,
  "accepted" : null,
  "basionymKey" : 2596383,
  "basionym" : "Bifidocarpus Cano, Guarro & R.F. Castañeda",
  "scientificName" : "Bifidocarpus Cano, Guarro & R.F. Castañeda",
  "canonicalName" : "Bifidocarpus",
  "vernacularName" : null,
  "authorship" : "Cano, Guarro & R.F. Castañeda",
  "nameType" : "WELLFORMED",
  "rank" : "GENUS",
  "origin" : "SOURCE",
  "taxonomicStatus" : "ACCEPTED",
  "nomenclaturalStatus" : [ ],
  "remarks" : null,
  "publishedIn" : "Mycotaxon 52(1): 53 (1994)",
  "accordingTo" : "The Catalogue of Life, 3rd January 2011",
  "numDescendants" : 2,
  "identifiers" : [ {
    "key" : null,
    "usageKey" : null,
    "datasetKey" : null,
    "identifier" : "119502115",
    "title" : null,
    "type" : "SOURCE_ID",
    "identifierLink" : null
  } ],
  "synonym" : false,
  "link" : null,
  "sourceId" : "119502115"
}