{
  "key" : 3456387,
  "kingdom" : "Fungi",
  "phylum" : "Ascomycota",
  "clazz" : "Sordariomycetes",
  "order" : null,
  "family" : null,
  "genus" : "Leptosporella",
  "subgenus" : null,
  "species" : "Leptosporella clelandii",
  "kingdomKey" : 5,
  "phylumKey" : 95,
  "classKey" : 320,
  "orderKey" : null,
  "familyKey" : null,
  "genusKey" : 3456376,
  "subgenusKey" : null,
  "speciesKey" : 3456387,
  "datasetKey" : "d7dddbf4-2cf0-4f39-9b2a-bb099caae36c",
  "constituentKey" : null,
  "nubKey" : 3456387,
  "parentKey" : 3456376,
  "parent" : "Leptosporella",
  "proParteKey" : null,
  "acceptedKey" : null,
  "accepted" : null,
  "basionymKey" : 3456387,
  "basionym" : "Leptosporella clelandii Hansf.",
  "scientificName" : "Leptosporella clelandii Hansf.",
  "canonicalName" : "Leptosporella clelandii",
  "vernacularName" : null,
  "authorship" : "Hansf.",
  "nameType" : "WELLFORMED",
  "rank" : "SPECIES",
  "origin" : "SOURCE",
  "taxonomicStatus" : "ACCEPTED",
  "nomenclaturalStatus" : [ ],
  "remarks" : null,
  "publishedIn" : "Kew Bull. 324 (1958)",
  "accordingTo" : "Index Fungorum",
  "numDescendants" : 0,
  "identifiers" : [ {
    "key" : null,
    "usageKey" : null,
    "datasetKey" : null,
    "identifier" : "109823870",
    "title" : null,
    "type" : "SOURCE_ID",
    "identifierLink" : null
  } ],
  "synonym" : false,
  "link" : null,
  "sourceId" : "109823870"
}