{
  "key" : 5265426,
  "kingdom" : "Fungi",
  "phylum" : "Ascomycota",
  "clazz" : "Dothideomycetes",
  "order" : null,
  "family" : "Saccardiaceae",
  "genus" : "Dictyonella",
  "subgenus" : null,
  "species" : "Dictyonella alangii",
  "kingdomKey" : 5,
  "phylumKey" : 95,
  "classKey" : 183,
  "orderKey" : null,
  "familyKey" : 5737,
  "genusKey" : 2625138,
  "subgenusKey" : null,
  "speciesKey" : 5265426,
  "datasetKey" : "d7dddbf4-2cf0-4f39-9b2a-bb099caae36c",
  "constituentKey" : null,
  "nubKey" : 5265426,
  "parentKey" : 2625138,
  "parent" : "Dictyonella",
  "proParteKey" : null,
  "acceptedKey" : null,
  "accepted" : null,
  "basionymKey" : 5265426,
  "basionym" : "Dictyonella alangii Hansf. & Thirum., 1948",
  "scientificName" : "Dictyonella alangii Hansf. & Thirum., 1948",
  "canonicalName" : "Dictyonella alangii",
  "vernacularName" : null,
  "authorship" : "Hansf. & Thirum., 1948",
  "nameType" : "WELLFORMED",
  "rank" : "SPECIES",
  "origin" : "SOURCE",
  "taxonomicStatus" : "ACCEPTED",
  "nomenclaturalStatus" : [ ],
  "remarks" : null,
  "publishedIn" : "Farlowia 3: 285 (1948)",
  "accordingTo" : "The Catalogue of Life, 3rd January 2011",
  "numDescendants" : 0,
  "identifiers" : [ {
    "key" : null,
    "usageKey" : null,
    "datasetKey" : null,
    "identifier" : "120296040",
    "title" : null,
    "type" : "SOURCE_ID",
    "identifierLink" : null
  } ],
  "synonym" : false,
  "link" : null,
  "sourceId" : "120296040"
}