{
  "key" : 7245062,
  "kingdom" : "Fungi",
  "phylum" : "Basidiomycota",
  "clazz" : "Agaricostilbomycetes",
  "order" : "Agaricostilbales",
  "family" : "Chionosphaeraceae",
  "genus" : "Stilbum",
  "subgenus" : null,
  "species" : "Stilbum gelatinosum",
  "kingdomKey" : 5,
  "phylumKey" : 34,
  "classKey" : 274,
  "orderKey" : 1143,
  "familyKey" : 3275,
  "genusKey" : 2523630,
  "subgenusKey" : null,
  "speciesKey" : 7245061,
  "datasetKey" : "d7dddbf4-2cf0-4f39-9b2a-bb099caae36c",
  "constituentKey" : null,
  "nubKey" : 7245062,
  "parentKey" : 7245061,
  "parent" : "Stilbum gelatinosum",
  "proParteKey" : null,
  "acceptedKey" : null,
  "accepted" : null,
  "basionymKey" : 7245062,
  "basionym" : "Stilbum gelatinosum var. gelatinosum",
  "scientificName" : "Stilbum gelatinosum var. gelatinosum",
  "canonicalName" : "Stilbum gelatinosum gelatinosum",
  "vernacularName" : null,
  "authorship" : "",
  "nameType" : "WELLFORMED",
  "rank" : "VARIETY",
  "origin" : "SOURCE",
  "taxonomicStatus" : "ACCEPTED",
  "nomenclaturalStatus" : [ ],
  "remarks" : null,
  "publishedIn" : null,
  "accordingTo" : "Index Fungorum",
  "numDescendants" : 0,
  "identifiers" : [ {
    "key" : null,
    "usageKey" : null,
    "datasetKey" : null,
    "identifier" : "109862749",
    "title" : null,
    "type" : "SOURCE_ID",
    "identifierLink" : null
  } ],
  "synonym" : false,
  "link" : null,
  "sourceId" : "109862749"
}