{
  "key" : 2523624,
  "kingdom" : "Fungi",
  "phylum" : "Basidiomycota",
  "clazz" : "Agaricomycetes",
  "order" : null,
  "family" : null,
  "genus" : "Akenomyces",
  "subgenus" : null,
  "species" : "Akenomyces costatus",
  "kingdomKey" : 5,
  "phylumKey" : 34,
  "classKey" : 186,
  "orderKey" : null,
  "familyKey" : null,
  "genusKey" : 2523623,
  "subgenusKey" : null,
  "speciesKey" : 2523624,
  "datasetKey" : "d7dddbf4-2cf0-4f39-9b2a-bb099caae36c",
  "constituentKey" : null,
  "nubKey" : 2523624,
  "parentKey" : 2523623,
  "parent" : "Akenomyces",
  "proParteKey" : null,
  "acceptedKey" : null,
  "accepted" : null,
  "basionymKey" : 2523624,
  "basionym" : "Akenomyces costatus D. Hornby",
  "scientificName" : "Akenomyces costatus D. Hornby",
  "canonicalName" : "Akenomyces costatus",
  "vernacularName" : null,
  "authorship" : "D. Hornby",
  "nameType" : "WELLFORMED",
  "rank" : "SPECIES",
  "origin" : "SOURCE",
  "taxonomicStatus" : "ACCEPTED",
  "nomenclaturalStatus" : [ ],
  "remarks" : null,
  "publishedIn" : "Trans. Br. mycol. Soc. 82(4): 653 (1984)",
  "accordingTo" : "The Catalogue of Life, 3rd January 2011",
  "numDescendants" : 2,
  "identifiers" : [ {
    "key" : null,
    "usageKey" : null,
    "datasetKey" : null,
    "identifier" : "120473993",
    "title" : null,
    "type" : "SOURCE_ID",
    "identifierLink" : null
  } ],
  "synonym" : false,
  "link" : null,
  "sourceId" : "120473993"
}