{
  "key" : 5489685,
  "kingdom" : "Fungi",
  "phylum" : "Ascomycota",
  "clazz" : "Eurotiomycetes",
  "order" : "Pyrenulales",
  "family" : "Celotheliaceae",
  "genus" : "Celothelium",
  "subgenus" : null,
  "species" : "Celothelium ischnobelum",
  "kingdomKey" : 5,
  "phylumKey" : 95,
  "classKey" : 178,
  "orderKey" : 1044,
  "familyKey" : 8353,
  "genusKey" : 2598873,
  "subgenusKey" : null,
  "speciesKey" : 2598874,
  "datasetKey" : "d7dddbf4-2cf0-4f39-9b2a-bb099caae36c",
  "constituentKey" : null,
  "nubKey" : 5489685,
  "parentKey" : 2598873,
  "parent" : "Celothelium",
  "proParteKey" : null,
  "acceptedKey" : 2598874,
  "accepted" : "Celothelium ischnobelum (Nyl.) M. B. Aguirre",
  "basionymKey" : null,
  "basionym" : null,
  "scientificName" : "Leptorhaphis carrollii A.L. Sm., 1911",
  "canonicalName" : "Leptorhaphis carrollii",
  "vernacularName" : null,
  "authorship" : "A.L. Sm., 1911",
  "nameType" : "WELLFORMED",
  "rank" : "SPECIES",
  "origin" : "SOURCE",
  "taxonomicStatus" : "SYNONYM",
  "nomenclaturalStatus" : [ ],
  "remarks" : null,
  "publishedIn" : null,
  "accordingTo" : "Interim Register of Marine and Nonmarine Genera",
  "numDescendants" : 0,
  "identifiers" : [ {
    "key" : null,
    "usageKey" : null,
    "datasetKey" : null,
    "identifier" : "101701201",
    "title" : null,
    "type" : "SOURCE_ID",
    "identifierLink" : null
  } ],
  "synonym" : true,
  "link" : null,
  "sourceId" : "101701201"
}