{
  "key" : 5258298,
  "kingdom" : "Fungi",
  "phylum" : "Ascomycota",
  "clazz" : null,
  "order" : null,
  "family" : null,
  "genus" : "Spegazzinia",
  "subgenus" : null,
  "species" : "Spegazzinia intermedia",
  "kingdomKey" : 5,
  "phylumKey" : 95,
  "classKey" : null,
  "orderKey" : null,
  "familyKey" : null,
  "genusKey" : 2591989,
  "subgenusKey" : null,
  "speciesKey" : 5258298,
  "datasetKey" : "d7dddbf4-2cf0-4f39-9b2a-bb099caae36c",
  "constituentKey" : null,
  "nubKey" : 5258298,
  "parentKey" : 2591989,
  "parent" : "Spegazzinia",
  "proParteKey" : null,
  "acceptedKey" : null,
  "accepted" : null,
  "basionymKey" : 5258298,
  "basionym" : "Spegazzinia intermedia M.B. Ellis, 1976",
  "scientificName" : "Spegazzinia intermedia M.B. Ellis, 1976",
  "canonicalName" : "Spegazzinia intermedia",
  "vernacularName" : null,
  "authorship" : "M.B. Ellis, 1976",
  "nameType" : "WELLFORMED",
  "rank" : "SPECIES",
  "origin" : "SOURCE",
  "taxonomicStatus" : "ACCEPTED",
  "nomenclaturalStatus" : [ ],
  "remarks" : null,
  "publishedIn" : "More Dematiaceous Hyphomycetes (Kew) 475 (1976)",
  "accordingTo" : "The Catalogue of Life, 3rd January 2011",
  "numDescendants" : 0,
  "identifiers" : [ {
    "key" : null,
    "usageKey" : null,
    "datasetKey" : null,
    "identifier" : "120223572",
    "title" : null,
    "type" : "SOURCE_ID",
    "identifierLink" : null
  } ],
  "synonym" : false,
  "link" : null,
  "sourceId" : "120223572"
}