{
  "key" : 6013272,
  "kingdom" : "Fungi",
  "phylum" : "Ascomycota",
  "clazz" : "Lecanoromycetes",
  "order" : "Peltigerales",
  "family" : "Collemataceae",
  "genus" : "Collema",
  "subgenus" : null,
  "species" : null,
  "kingdomKey" : 5,
  "phylumKey" : 95,
  "classKey" : 180,
  "orderKey" : 1055,
  "familyKey" : 8377,
  "genusKey" : 2600808,
  "subgenusKey" : null,
  "speciesKey" : null,
  "datasetKey" : "d7dddbf4-2cf0-4f39-9b2a-bb099caae36c",
  "constituentKey" : null,
  "nubKey" : 6013272,
  "parentKey" : 8377,
  "parent" : "Collemataceae",
  "proParteKey" : null,
  "acceptedKey" : 2600808,
  "accepted" : "Collema F.H. Wiggers, 1780",
  "basionymKey" : 6013272,
  "basionym" : "Collematomyces E.A. Thomas ex Cif. & Tomas.",
  "scientificName" : "Collematomyces E.A. Thomas ex Cif. & Tomas.",
  "canonicalName" : "Collematomyces",
  "vernacularName" : null,
  "authorship" : "E.A. Thomas ex Cif. & Tomas.",
  "nameType" : "WELLFORMED",
  "rank" : "GENUS",
  "origin" : "SOURCE",
  "taxonomicStatus" : "SYNONYM",
  "nomenclaturalStatus" : [ ],
  "remarks" : null,
  "publishedIn" : "Atti Ist. bot. Univ. Lab. crittog. Pavia, Sér. 5 10(1): 70 (1953)",
  "accordingTo" : "Index Fungorum",
  "numDescendants" : 0,
  "identifiers" : [ {
    "key" : null,
    "usageKey" : null,
    "datasetKey" : null,
    "identifier" : "110218460",
    "title" : null,
    "type" : "SOURCE_ID",
    "identifierLink" : null
  } ],
  "synonym" : true,
  "link" : null,
  "sourceId" : "110218460"
}