{
  "key" : 6124353,
  "kingdom" : "Fungi",
  "phylum" : "Basidiomycota",
  "clazz" : "Agaricomycetes",
  "order" : "Agaricales",
  "family" : "Tricholomataceae",
  "genus" : "Phyllotopsis",
  "subgenus" : null,
  "species" : "Phyllotopsis nidulens",
  "kingdomKey" : 5,
  "phylumKey" : 34,
  "classKey" : 186,
  "orderKey" : 1499,
  "familyKey" : 8787,
  "genusKey" : 2531624,
  "subgenusKey" : null,
  "speciesKey" : 6124353,
  "datasetKey" : "d7dddbf4-2cf0-4f39-9b2a-bb099caae36c",
  "constituentKey" : null,
  "nubKey" : 6124353,
  "parentKey" : 2531624,
  "parent" : "Phyllotopsis",
  "proParteKey" : null,
  "acceptedKey" : null,
  "accepted" : null,
  "basionymKey" : null,
  "basionym" : null,
  "scientificName" : "Phyllotopsis nidulens (Pers. ex Fr.) Sing.",
  "canonicalName" : "Phyllotopsis nidulens",
  "vernacularName" : null,
  "authorship" : "Sing. (Pers. ex Fr.)",
  "nameType" : "WELLFORMED",
  "rank" : "SPECIES",
  "origin" : "SOURCE",
  "taxonomicStatus" : "ACCEPTED",
  "nomenclaturalStatus" : [ ],
  "remarks" : null,
  "publishedIn" : null,
  "accordingTo" : "The National Checklist of Taiwan",
  "numDescendants" : 0,
  "identifiers" : [ {
    "key" : null,
    "usageKey" : null,
    "datasetKey" : null,
    "identifier" : "110810154",
    "title" : null,
    "type" : "SOURCE_ID",
    "identifierLink" : null
  } ],
  "synonym" : false,
  "link" : null,
  "sourceId" : "110810154"
}