{
  "key" : 2533132,
  "kingdom" : "Fungi",
  "phylum" : "Basidiomycota",
  "clazz" : "Agaricomycetes",
  "order" : "Agaricales",
  "family" : "Strophariaceae",
  "genus" : "Agrocybe",
  "subgenus" : null,
  "species" : "Agrocybe molesta",
  "kingdomKey" : 5,
  "phylumKey" : 34,
  "classKey" : 186,
  "orderKey" : 1499,
  "familyKey" : 4186,
  "genusKey" : 2527828,
  "subgenusKey" : null,
  "speciesKey" : 2533127,
  "datasetKey" : "d7dddbf4-2cf0-4f39-9b2a-bb099caae36c",
  "constituentKey" : null,
  "nubKey" : 2533132,
  "parentKey" : 2527828,
  "parent" : "Agrocybe",
  "proParteKey" : null,
  "acceptedKey" : 2533127,
  "accepted" : "Agrocybe molesta (Lasch) Singer, 1978",
  "basionymKey" : 2533129,
  "basionym" : "Pholiota dura var. xanthophylla Bres., 1892",
  "scientificName" : "Agrocybe dura var. xanthophylla (Bres.) P.D. Orton, 1960",
  "canonicalName" : "Agrocybe dura xanthophylla",
  "vernacularName" : null,
  "authorship" : "P.D. Orton, 1960 (Bres.)",
  "nameType" : "WELLFORMED",
  "rank" : "VARIETY",
  "origin" : "SOURCE",
  "taxonomicStatus" : "SYNONYM",
  "nomenclaturalStatus" : [ ],
  "remarks" : null,
  "publishedIn" : "Trans. Br. mycol. Soc. 43(2): 174 (1960)",
  "accordingTo" : "The Catalogue of Life, 3rd January 2011",
  "numDescendants" : 0,
  "identifiers" : [ {
    "key" : null,
    "usageKey" : null,
    "datasetKey" : null,
    "identifier" : "120266072",
    "title" : null,
    "type" : "SOURCE_ID",
    "identifierLink" : null
  } ],
  "synonym" : true,
  "link" : null,
  "sourceId" : "120266072"
}