{
  "key" : 3438147,
  "kingdom" : "Fungi",
  "phylum" : "Ascomycota",
  "clazz" : "Lecanoromycetes",
  "order" : "Lecanorales",
  "family" : "Lecideaceae",
  "genus" : "Lecidea",
  "subgenus" : null,
  "species" : "Lecidea cinereonigra",
  "kingdomKey" : 5,
  "phylumKey" : 95,
  "classKey" : 180,
  "orderKey" : 1048,
  "familyKey" : 8296,
  "genusKey" : 2569865,
  "subgenusKey" : null,
  "speciesKey" : 3438147,
  "datasetKey" : "d7dddbf4-2cf0-4f39-9b2a-bb099caae36c",
  "constituentKey" : null,
  "nubKey" : 3438147,
  "parentKey" : 2569865,
  "parent" : "Lecidea",
  "proParteKey" : null,
  "acceptedKey" : null,
  "accepted" : null,
  "basionymKey" : 3438147,
  "basionym" : "Lecidea cinereonigra Vain.",
  "scientificName" : "Lecidea cinereonigra Vain.",
  "canonicalName" : "Lecidea cinereonigra",
  "vernacularName" : null,
  "authorship" : "Vain.",
  "nameType" : "WELLFORMED",
  "rank" : "SPECIES",
  "origin" : "SOURCE",
  "taxonomicStatus" : "ACCEPTED",
  "nomenclaturalStatus" : [ ],
  "remarks" : null,
  "publishedIn" : "Acta Soc. Fauna Flora fenn. 7(2): 10 (1890)",
  "accordingTo" : "Index Fungorum",
  "numDescendants" : 0,
  "identifiers" : [ {
    "key" : null,
    "usageKey" : null,
    "datasetKey" : null,
    "identifier" : "110127979",
    "title" : null,
    "type" : "SOURCE_ID",
    "identifierLink" : null
  } ],
  "synonym" : false,
  "link" : null,
  "sourceId" : "110127979"
}