{
  "key" : 3201538,
  "kingdom" : "Chromista",
  "phylum" : "Haptophyta",
  "clazz" : "Prymnesiophyceae",
  "order" : "Coccosphaerales",
  "family" : "Rhabdosphaeraceae",
  "genus" : "Algirosphaera",
  "subgenus" : null,
  "species" : "Algirosphaera quadricornu",
  "kingdomKey" : 4,
  "phylumKey" : 70,
  "classKey" : 258,
  "orderKey" : 1084,
  "familyKey" : 7111,
  "genusKey" : 3201531,
  "subgenusKey" : null,
  "speciesKey" : 3201537,
  "datasetKey" : "d7dddbf4-2cf0-4f39-9b2a-bb099caae36c",
  "constituentKey" : null,
  "nubKey" : 3201538,
  "parentKey" : 3201531,
  "parent" : "Algirosphaera",
  "proParteKey" : null,
  "acceptedKey" : 3201537,
  "accepted" : "Algirosphaera quadricornu (Schiller) Norris",
  "basionymKey" : null,
  "basionym" : null,
  "scientificName" : "Syracosphaera quatricornu Schiller",
  "canonicalName" : "Syracosphaera quatricornu",
  "vernacularName" : null,
  "authorship" : "Schiller",
  "nameType" : "WELLFORMED",
  "rank" : "SPECIES",
  "origin" : "SOURCE",
  "taxonomicStatus" : "SYNONYM",
  "nomenclaturalStatus" : [ ],
  "remarks" : null,
  "publishedIn" : null,
  "accordingTo" : "The Catalogue of Life, 3rd January 2011",
  "numDescendants" : 0,
  "identifiers" : [ {
    "key" : null,
    "usageKey" : null,
    "datasetKey" : null,
    "identifier" : "119671065",
    "title" : null,
    "type" : "SOURCE_ID",
    "identifierLink" : null
  } ],
  "synonym" : true,
  "link" : null,
  "sourceId" : "119671065"
}