{
  "key" : 3279428,
  "kingdom" : "Fungi",
  "phylum" : "Ascomycota",
  "clazz" : "Dothideomycetes",
  "order" : "Capnodiales",
  "family" : "Mycosphaerellaceae",
  "genus" : "Cercosporina",
  "subgenus" : null,
  "species" : "Cercosporina trigonellae",
  "kingdomKey" : 5,
  "phylumKey" : 95,
  "classKey" : 183,
  "orderKey" : 1262,
  "familyKey" : 4797,
  "genusKey" : 7254393,
  "subgenusKey" : null,
  "speciesKey" : 3279428,
  "datasetKey" : "d7dddbf4-2cf0-4f39-9b2a-bb099caae36c",
  "constituentKey" : null,
  "nubKey" : 3279428,
  "parentKey" : 7254393,
  "parent" : "Cercosporina",
  "proParteKey" : null,
  "acceptedKey" : null,
  "accepted" : null,
  "basionymKey" : 5507517,
  "basionym" : "Cercospora trigonellae Maubl.",
  "scientificName" : "Cercosporina trigonellae (Maubl.) Sacc.",
  "canonicalName" : "Cercosporina trigonellae",
  "vernacularName" : null,
  "authorship" : "Sacc. (Maubl.)",
  "nameType" : "WELLFORMED",
  "rank" : "SPECIES",
  "origin" : "SOURCE",
  "taxonomicStatus" : "ACCEPTED",
  "nomenclaturalStatus" : [ ],
  "remarks" : null,
  "publishedIn" : null,
  "accordingTo" : "Index Fungorum",
  "numDescendants" : 0,
  "identifiers" : [ {
    "key" : null,
    "usageKey" : null,
    "datasetKey" : null,
    "identifier" : "109959938",
    "title" : null,
    "type" : "SOURCE_ID",
    "identifierLink" : null
  } ],
  "synonym" : false,
  "link" : null,
  "sourceId" : "109959938"
}