{
  "key" : 2528045,
  "kingdom" : "Fungi",
  "phylum" : "Basidiomycota",
  "clazz" : "Agaricomycetes",
  "order" : "Agaricales",
  "family" : "Inocybaceae",
  "genus" : "Inocybe",
  "subgenus" : null,
  "species" : "Inocybe dunensis",
  "kingdomKey" : 5,
  "phylumKey" : 34,
  "classKey" : 186,
  "orderKey" : 1499,
  "familyKey" : 4177,
  "genusKey" : 2527866,
  "subgenusKey" : null,
  "speciesKey" : 2528053,
  "datasetKey" : "d7dddbf4-2cf0-4f39-9b2a-bb099caae36c",
  "constituentKey" : null,
  "nubKey" : 2528045,
  "parentKey" : 2527866,
  "parent" : "Inocybe",
  "proParteKey" : null,
  "acceptedKey" : 2528053,
  "accepted" : "Inocybe dunensis P.D. Orton, 1960",
  "basionymKey" : 2528048,
  "basionym" : "Agaricus maritimus Fr., 1818",
  "scientificName" : "Inocybe maritima P. Karst., 1879",
  "canonicalName" : "Inocybe maritima",
  "vernacularName" : null,
  "authorship" : "P. Karst., 1879",
  "nameType" : "WELLFORMED",
  "rank" : "SPECIES",
  "origin" : "SOURCE",
  "taxonomicStatus" : "SYNONYM",
  "nomenclaturalStatus" : [ ],
  "remarks" : null,
  "publishedIn" : "Bidr. Känn. Finl. Nat. Folk 32: 457 (1879)",
  "accordingTo" : "The Catalogue of Life, 3rd January 2011",
  "numDescendants" : 0,
  "identifiers" : [ {
    "key" : null,
    "usageKey" : null,
    "datasetKey" : null,
    "identifier" : "120274136",
    "title" : null,
    "type" : "SOURCE_ID",
    "identifierLink" : null
  } ],
  "synonym" : true,
  "link" : null,
  "sourceId" : "120274136"
}