{
  "key" : 3412038,
  "kingdom" : "Fungi",
  "phylum" : "Ascomycota",
  "clazz" : "Lecanoromycetes",
  "order" : "Pertusariales",
  "family" : "Pertusariaceae",
  "genus" : "Pertusaria",
  "subgenus" : null,
  "species" : "Pertusaria remota",
  "kingdomKey" : 5,
  "phylumKey" : 95,
  "classKey" : 180,
  "orderKey" : 1051,
  "familyKey" : 4113,
  "genusKey" : 2599923,
  "subgenusKey" : null,
  "speciesKey" : 3412038,
  "datasetKey" : "d7dddbf4-2cf0-4f39-9b2a-bb099caae36c",
  "constituentKey" : null,
  "nubKey" : 3412038,
  "parentKey" : 2599923,
  "parent" : "Pertusaria",
  "proParteKey" : null,
  "acceptedKey" : null,
  "accepted" : null,
  "basionymKey" : 3412038,
  "basionym" : "Pertusaria remota A.W. Archer",
  "scientificName" : "Pertusaria remota A.W. Archer",
  "canonicalName" : "Pertusaria remota",
  "vernacularName" : null,
  "authorship" : "A.W. Archer",
  "nameType" : "WELLFORMED",
  "rank" : "SPECIES",
  "origin" : "SOURCE",
  "taxonomicStatus" : "ACCEPTED",
  "nomenclaturalStatus" : [ ],
  "remarks" : null,
  "publishedIn" : "Mycotaxon 41(1): 238 (1991)",
  "accordingTo" : "Index Fungorum",
  "numDescendants" : 0,
  "identifiers" : [ {
    "key" : null,
    "usageKey" : null,
    "datasetKey" : null,
    "identifier" : "109883013",
    "title" : null,
    "type" : "SOURCE_ID",
    "identifierLink" : null
  } ],
  "synonym" : false,
  "link" : null,
  "sourceId" : "109883013"
}