{
  "key" : 2581965,
  "kingdom" : "Fungi",
  "phylum" : "Ascomycota",
  "clazz" : "Leotiomycetes",
  "order" : "Helotiales",
  "family" : "Helotiaceae",
  "genus" : "Phaeohelotium",
  "subgenus" : null,
  "species" : "Phaeohelotium trabinellum",
  "kingdomKey" : 5,
  "phylumKey" : 95,
  "classKey" : 179,
  "orderKey" : 1052,
  "familyKey" : 8381,
  "genusKey" : 2581948,
  "subgenusKey" : null,
  "speciesKey" : 2581965,
  "datasetKey" : "d7dddbf4-2cf0-4f39-9b2a-bb099caae36c",
  "constituentKey" : null,
  "nubKey" : 2581965,
  "parentKey" : 2581948,
  "parent" : "Phaeohelotium",
  "proParteKey" : null,
  "acceptedKey" : null,
  "accepted" : null,
  "basionymKey" : 5256287,
  "basionym" : "Helotium trabinellum P. Karst., 1871",
  "scientificName" : "Phaeohelotium trabinellum (P. Karst.) Dennis, 1971",
  "canonicalName" : "Phaeohelotium trabinellum",
  "vernacularName" : null,
  "authorship" : "Dennis, 1971 (P. Karst.)",
  "nameType" : "WELLFORMED",
  "rank" : "SPECIES",
  "origin" : "SOURCE",
  "taxonomicStatus" : "ACCEPTED",
  "nomenclaturalStatus" : [ ],
  "remarks" : null,
  "publishedIn" : "Kew Bull. 25(2): 354 (1971)",
  "accordingTo" : "The Catalogue of Life, 3rd January 2011",
  "numDescendants" : 2,
  "identifiers" : [ {
    "key" : null,
    "usageKey" : null,
    "datasetKey" : null,
    "identifier" : "120222782",
    "title" : null,
    "type" : "SOURCE_ID",
    "identifierLink" : null
  } ],
  "synonym" : false,
  "link" : null,
  "sourceId" : "120222782"
}