{
  "key" : 5493581,
  "kingdom" : "Fungi",
  "phylum" : "Ascomycota",
  "clazz" : null,
  "order" : null,
  "family" : null,
  "genus" : "Medusula",
  "subgenus" : null,
  "species" : "Medusula disjectans",
  "kingdomKey" : 5,
  "phylumKey" : 95,
  "classKey" : null,
  "orderKey" : null,
  "familyKey" : null,
  "genusKey" : 3269569,
  "subgenusKey" : null,
  "speciesKey" : 5493581,
  "datasetKey" : "d7dddbf4-2cf0-4f39-9b2a-bb099caae36c",
  "constituentKey" : null,
  "nubKey" : 5493581,
  "parentKey" : 3269569,
  "parent" : "Medusula",
  "proParteKey" : null,
  "acceptedKey" : null,
  "accepted" : null,
  "basionymKey" : 5493581,
  "basionym" : "Medusula disjectans Nyl.",
  "scientificName" : "Medusula disjectans Nyl.",
  "canonicalName" : "Medusula disjectans",
  "vernacularName" : null,
  "authorship" : "Nyl.",
  "nameType" : "WELLFORMED",
  "rank" : "SPECIES",
  "origin" : "SOURCE",
  "taxonomicStatus" : "ACCEPTED",
  "nomenclaturalStatus" : [ ],
  "remarks" : null,
  "publishedIn" : "Lich. Japon. 87 (1890)",
  "accordingTo" : "Index Fungorum",
  "numDescendants" : 0,
  "identifiers" : [ {
    "key" : null,
    "usageKey" : null,
    "datasetKey" : null,
    "identifier" : "110194008",
    "title" : null,
    "type" : "SOURCE_ID",
    "identifierLink" : null
  } ],
  "synonym" : false,
  "link" : null,
  "sourceId" : "110194008"
}